airportsdata/__init__.py
airportsdata/airports.csv
airportsdata/iata_macs.csv
airportsdata/py.typed
airportsdata-20250811.dist-info/licenses/LICENSE
airportsdata-20250811.dist-info/METADATA
airportsdata-20250811.dist-info/WHEEL
airportsdata-20250811.dist-info/top_level.txt
airportsdata-20250811.dist-info/RECORD
