Metadata-Version: 2.4
Name: airportsdata
Version: 20250811
Summary: Extensive database of location and timezone data for nearly every airport and landing strip in the world.
Author-email: Mike Borsetti <mike+airportsdata@borsetti.com>
Maintainer-email: Mike Borsetti <mike+airportsdata@borsetti.com>
License: The MIT License (MIT)
Project-URL: Documentation, https://github.com/mborsetti/airportsdata/blob/main/README.rst
Project-URL: Repository, https://github.com/mborsetti/airportsdata/
Project-URL: Database (csv), https://github.com/mborsetti/airportsdata/blob/main/airportsdata/airports.csv
Project-URL: Changelog, https://github.com/mborsetti/airportsdata/blob/main/CHANGELOG.rst
Project-URL: Issues, https://github.com/mborsetti/airportsdata/issues
Project-URL: CI, https://github.com/mborsetti/airportsdata/actions
Keywords: airports,aerodromes,ICAO,IATA
Classifier: Development Status :: 5 - Production/Stable
Classifier: Programming Language :: Python
Classifier: Programming Language :: Python :: 3
Classifier: Programming Language :: Python :: 3.10
Classifier: Programming Language :: Python :: 3.11
Classifier: Programming Language :: Python :: 3.12
Classifier: Programming Language :: Python :: 3.13
Classifier: Operating System :: OS Independent
Classifier: Topic :: Database
Classifier: Intended Audience :: Developers
Classifier: Typing :: Typed
Requires-Python: >=3.9
License-File: LICENSE
Dynamic: license-file
